{
    "type": "generic",
    "pools": [
        {
            "rolls": 1,
            "entries": [
                {
                    "type": "item",
                    "name": "curseofpandora:barbaric_blood",
                    "weight": 1
                },
                {
                    "type": "item",
                    "name": "curseofpandora:rotten_spine",
                    "weight": 1
                },
                {
                    "type": "item",
                    "name": "curseofpandora:eroded_spine",
                    "weight": 1
                },
                {
                    "type": "item",
                    "name": "curseofpandora:dried_spine",
                    "weight": 1
                },
                {
                    "type": "item",
                    "name": "curseofpandora:evil_spine",
                    "weight": 1
                },
                {
                    "type": "item",
                    "name": "curseofpandora:rotten_brain",
                    "weight": 1
                },
                {
                    "type": "item",
                    "name": "curseofpandora:eroded_brain",
                    "weight": 1
                },
                {
                    "type": "item",
                    "name": "curseofpandora:dried_brain",
                    "weight": 1
                }
            ]
        }
    ]

}